<?xml version="1.0" encoding="utf-8"?>
<Achievements xmlns="Ambient.Domain"
              xmlns:xsi="http://www.w3.org/2001/XMLSchema-instance"
              xsi:schemaLocation="Ambient.Domain ..\..\..\..\DefinitionXsd\Gameplay\Gameplay.xsd">

    <!-- ========================================
         GAME ACHIEVEMENTS
         Event-sourced achievements powered by Saga transaction logs
         Steam-compatible format (uppercase RefNames, underscores)
         ======================================== -->

    <!-- ===== COMBAT ACHIEVEMENTS ===== -->
    <!-- Shadow hunting progression -->

    <Achievement RefName="ACH_FIRST_SHADOW" DisplayName="Shadow Slayer"
                 Description="Defeated your first dark creature">
        <Criteria Type="CharactersDefeated" Threshold="1" />
    </Achievement>

    <Achievement RefName="ACH_SHADOW_HUNTER_10" DisplayName="Novice Shadow Hunter"
                 Description="Defeated 10 dark creatures">
        <Criteria Type="CharactersDefeated" Threshold="10" />
    </Achievement>

    <Achievement RefName="ACH_SHADOW_HUNTER_50" DisplayName="Experienced Shadow Hunter"
                 Description="Defeated 50 dark creatures">
        <Criteria Type="CharactersDefeated" Threshold="50" />
    </Achievement>

    <Achievement RefName="ACH_SHADOW_HUNTER_100" DisplayName="Master Shadow Hunter"
                 Description="Defeated 100 dark creatures - a true hero">
        <Criteria Type="CharactersDefeated" Threshold="100" />
    </Achievement>

    <!-- ===== BOSS ACHIEVEMENTS ===== -->
    <!-- Specific named boss encounters -->

    <Achievement RefName="ACH_SHADOW_SELF_DEFEATED" DisplayName="Power from Within"
                 Description="Defeated your dark doppelganger in battle and gained its power">
        <Criteria Type="CharactersDefeatedByRef" CharacterRef="Boss_Dark_Doppelganger" Threshold="1" />
    </Achievement>

    <Achievement RefName="ACH_SHRINE_GUARDIAN_DEFEATED" DisplayName="Oakvale's Blessing"
                 Description="Defeated the Divine Guardian and earned divine blessing">
        <Criteria Type="CharactersDefeatedByRef" CharacterRef="Boss_Temple_Guardian" Threshold="1" />
    </Achievement>

    <Achievement RefName="ACH_GOLDEN_HAND_DEFEATED" DisplayName="Strike It Rich"
                 Description="Defeated the rare Golden Hand Shadow before it fled">
        <Criteria Type="CharactersDefeatedByRef" CharacterRef="Boss_Golden_Hand" Threshold="1" />
    </Achievement>

    <Achievement RefName="ACH_REAPER_DEFEATED" DisplayName="Death Defied"
                 Description="Defeated The Reaper - death itself could not claim you">
        <Criteria Type="CharactersDefeatedByRef" CharacterRef="Boss_Reaper" Threshold="1" />
    </Achievement>

    <!-- Mini-boss achievements -->

    <Achievement RefName="ACH_CONTRARIAN_DEFEATED" DisplayName="Rebellion Crushed"
                 Description="Defeated the Contrarian King">
        <Criteria Type="CharactersDefeatedByRef" CharacterRef="Fiend_Contrarian" Threshold="1" />
    </Achievement>

    <Achievement RefName="ACH_DESIROUS_DEFEATED" DisplayName="Greed Vanquished"
                 Description="Defeated the Desirous Beast">
        <Criteria Type="CharactersDefeatedByRef" CharacterRef="Wraith_Desirous" Threshold="1" />
    </Achievement>

    <!-- ===== DISCOVERY ACHIEVEMENTS ===== -->
    <!-- Exploring the sacred grounds of Oakvale -->

    <Achievement RefName="ACH_SHRINE_PILGRIM" DisplayName="Temple Pilgrim"
                 Description="Discovered 5 sagas in Ancient">
        <Criteria Type="SagaArcsDiscovered" Threshold="5" />
    </Achievement>

    <Achievement RefName="ACH_SHRINE_DEVOTEE" DisplayName="Temple Devotee"
                 Description="Discovered 15 sagas in Ancient">
        <Criteria Type="SagaArcsDiscovered" Threshold="15" />
    </Achievement>

    <Achievement RefName="ACH_SHRINE_MASTER" DisplayName="Temple Master"
                 Description="Discovered 30 sagas - mastered the sacred grounds">
        <Criteria Type="SagaArcsDiscovered" Threshold="30" />
    </Achievement>

    <Achievement RefName="ACH_LANDMARK_SEEKER" DisplayName="Landmark Seeker"
                 Description="Discovered 10 landmarks in Ancient">
        <Criteria Type="LandmarksDiscovered" Threshold="10" />
    </Achievement>

    <Achievement RefName="ACH_INNER_SHRINE_FOUND" DisplayName="Inner Sanctum"
                 Description="Discovered Kōtai Jingū (Naikū) - the Inner Temple">
        <Criteria Type="SagaArcsDiscovered" Threshold="1" />
    </Achievement>

    <Achievement RefName="ACH_OUTER_SHRINE_FOUND" DisplayName="Outer Gates"
                 Description="Discovered Toyōke Daijingū (Gekū) - the Outer Temple">
        <Criteria Type="SagaArcsDiscovered" Threshold="1" />
    </Achievement>

    <!-- ===== SOCIAL ACHIEVEMENTS ===== -->
    <!-- Dialogue and character interactions -->

    <Achievement RefName="ACH_SHADOW_WHISPERER" DisplayName="Shadow Whisperer"
                 Description="Completed 5 conversations with Shadow entities">
        <Criteria Type="DialogueTreesCompleted" Threshold="5" />
    </Achievement>

    <Achievement RefName="ACH_SILVER_TONGUE" DisplayName="Silver Tongue"
                 Description="Completed 10 conversations">
        <Criteria Type="DialogueTreesCompleted" Threshold="10" />
    </Achievement>

    <Achievement RefName="ACH_MASTER_DIPLOMAT" DisplayName="Master Diplomat"
                 Description="Completed 25 conversations - a true communicator">
        <Criteria Type="DialogueTreesCompleted" Threshold="25" />
    </Achievement>

    <Achievement RefName="ACH_SOCIAL_BUTTERFLY" DisplayName="Social Butterfly"
                 Description="Met 10 different characters">
        <Criteria Type="UniqueCharactersMet" Threshold="10" />
    </Achievement>

    <Achievement RefName="ACH_PEOPLE_PERSON" DisplayName="People Person"
                 Description="Met 20 different characters">
        <Criteria Type="UniqueCharactersMet" Threshold="20" />
    </Achievement>

    <Achievement RefName="ACH_CHATTY" DisplayName="Chatty"
                 Description="Visited 100 dialogue nodes - enjoy deep conversations">
        <Criteria Type="DialogueNodesVisited" Threshold="100" />
    </Achievement>

    <!-- ===== QUEST TOKEN ACHIEVEMENTS ===== -->
    <!-- Quest progression and completion -->

    <Achievement RefName="ACH_QUEST_BEGINNER" DisplayName="Quest Beginner"
                 Description="Earned 5 quest tokens">
        <Criteria Type="QuestTokensEarned" Threshold="5" />
    </Achievement>

    <Achievement RefName="ACH_QUEST_ENTHUSIAST" DisplayName="Quest Enthusiast"
                 Description="Earned 15 quest tokens">
        <Criteria Type="QuestTokensEarned" Threshold="15" />
    </Achievement>

    <Achievement RefName="ACH_QUEST_MASTER" DisplayName="Quest Master"
                 Description="Earned 30 quest tokens - completed the expedition">
        <Criteria Type="QuestTokensEarned" Threshold="30" />
    </Achievement>

    <!-- Specific quest completion achievements -->

    <Achievement RefName="ACH_SHADOW_SELF_ACCEPTED" DisplayName="Facing Yourself"
                 Description="Accepted your Dark Doppelganger without fighting - confronted the truth within">
        <Criteria Type="QuestTokensEarned" QuestTokenRef="ShadowSelfAccepted" Threshold="1" />
    </Achievement>

    <Achievement RefName="ACH_PILGRIMAGE_COMPLETE" DisplayName="Sacred Pilgrimage"
                 Description="Completed the sacred pilgrimage to both Inner and Outer Temples">
        <Criteria Type="QuestTokensEarned" QuestTokenRef="PilgrimageComplete" Threshold="1" />
    </Achievement>

    <Achievement RefName="ACH_MET_MYSTERIOUS_FOX" DisplayName="Divine Messenger"
                 Description="Encountered the mysterious fox at the temple">
        <Criteria Type="QuestTokensEarned" QuestTokenRef="MetMysteriousFox" Threshold="1" />
    </Achievement>

    <!-- ===== SIDE QUEST ACHIEVEMENTS ===== -->
    <!-- Completionist achievements for all 20 side quests -->

    <Achievement RefName="ACH_SIDE_QUESTS_5" DisplayName="Shadow Hunter Initiate"
                 Description="Completed 5 side quest Shadow hunts">
        <Criteria Type="QuestTokensEarned" Threshold="5" />
    </Achievement>

    <Achievement RefName="ACH_SIDE_QUESTS_10" DisplayName="Shadow Hunter Veteran"
                 Description="Completed 10 side quest Shadow hunts">
        <Criteria Type="QuestTokensEarned" Threshold="10" />
    </Achievement>

    <Achievement RefName="ACH_SIDE_QUESTS_20" DisplayName="Shadow Hunt Perfect"
                 Description="Completed all 20 side quest Shadow hunts - true dedication">
        <Criteria Type="QuestTokensEarned" Threshold="20" />
    </Achievement>

    <!-- ===== AFFINITY/COLLECTION ACHIEVEMENTS ===== -->
    <!-- power collection and spell mastery -->

    <Achievement RefName="ACH_FIRE_AFFINITY" DisplayName="Fire Wielder"
                 Description="Unlocked the Fire (Fire) affinity">
        <Criteria Type="QuestTokensEarned" QuestTokenRef="UnlockedFire" Threshold="1" />
    </Achievement>

    <Achievement RefName="ACH_ICE_AFFINITY" DisplayName="Ice Wielder"
                 Description="Unlocked the Frost (Ice) affinity">
        <Criteria Type="QuestTokensEarned" QuestTokenRef="UnlockedFrost" Threshold="1" />
    </Achievement>

    <Achievement RefName="ACH_ELECTRIC_AFFINITY" DisplayName="Electric Wielder"
                 Description="Unlocked the Spark (Electric) affinity">
        <Criteria Type="QuestTokensEarned" QuestTokenRef="UnlockedSpark" Threshold="1" />
    </Achievement>

    <Achievement RefName="ACH_WIND_AFFINITY" DisplayName="Wind Wielder"
                 Description="Unlocked the Breeze (Wind) affinity">
        <Criteria Type="QuestTokensEarned" QuestTokenRef="UnlockedBreeze" Threshold="1" />
    </Achievement>

    <Achievement RefName="ACH_DIVINE_AFFINITY" DisplayName="Divine Blessing"
                 Description="Unlocked the Divine affinity - blessed by Amaterasu">
        <Criteria Type="QuestTokensEarned" QuestTokenRef="UnlockedDivine" Threshold="1" />
    </Achievement>

    <Achievement RefName="ACH_AFFINITY_COLLECTOR" DisplayName="power Collector"
                 Description="Unlocked 5 different affinities - building your power collection">
        <Criteria Type="QuestTokensEarned" Threshold="5" />
    </Achievement>

    <Achievement RefName="ACH_WILD_CARD" DisplayName="versatile"
                 Description="Unlocked all 8 affinities - mastered the power of the versatile">
        <Criteria Type="QuestTokensEarned" Threshold="8" />
    </Achievement>

    <!-- ===== SPECIAL ACHIEVEMENTS ===== -->
    <!-- Miscellaneous and completion achievements -->

    <Achievement RefName="ACH_TRIGGER_EXPLORER" DisplayName="Zone Explorer"
                 Description="Activated 50 trigger zones exploring Ancient">
        <Criteria Type="SagaTriggersActivated" Threshold="50" />
    </Achievement>

    <Achievement RefName="ACH_TRIGGER_VETERAN" DisplayName="Zone Veteran"
                 Description="Activated 100 trigger zones - thorough explorer">
        <Criteria Type="SagaTriggersActivated" Threshold="100" />
    </Achievement>

    <Achievement RefName="ACH_OAKVALE_EXPEDITION_COMPLETE" DisplayName="Village Trip Success"
                 Description="Completed the Oakvale expedition and returned safely">
        <Criteria Type="SagaArcsCompleted" Threshold="1" />
    </Achievement>

    <Achievement RefName="ACH_OAKVALE_COMPLETIONIST" DisplayName="Oakvale Completionist"
                 Description="Completed all Sagas in Oakvale - achieved perfection">
        <Criteria Type="SagaArcsCompleted" Threshold="35" />
    </Achievement>

    <!-- ===== CHALLENGE ACHIEVEMENTS ===== -->
    <!-- Difficult milestones -->

    <Achievement RefName="ACH_ALL_BOSSES" DisplayName="Boss Slayer Legend"
                 Description="Defeated all 4 major bosses in Ancient">
        <Criteria Type="CharactersDefeated" Threshold="4" />
    </Achievement>

    <Achievement RefName="ACH_SHADOW_LEGEND" DisplayName="Shadow Legend"
                 Description="Defeated 200 dark creatures - legendary warrior">
        <Criteria Type="CharactersDefeated" Threshold="200" />
    </Achievement>

</Achievements>
